e_encryption/__init__.py
e_encryption/e_encryption.py
easy_encryption/__init__.py
easy_encryption/easyencryption.py
e_encryption-0.0.4.dist-info/METADATA
e_encryption-0.0.4.dist-info/WHEEL
e_encryption-0.0.4.dist-info/top_level.txt
e_encryption-0.0.4.dist-info/RECORD
