Metadata-Version: 2.1
Name: e-encryption
Version: 0.0.4
Summary: Easy encryption and decryption
Author: Jeff Aguilar
Author-email: jeff.aguilar.06@gmail.com
License: MIT
Keywords: encryption,decryption
Classifier: Development Status :: 3 - Alpha
Classifier: Intended Audience :: Developers
Classifier: Topic :: Software Development :: Build Tools
Classifier: License :: OSI Approved :: MIT License
Classifier: Programming Language :: Python :: 3.6
Classifier: Programming Language :: Python :: 3.7
Classifier: Programming Language :: Python :: 3.8
Classifier: Programming Language :: Python :: 3.9
Classifier: Programming Language :: Python :: 3.10
Requires-Dist: cryptography
